nbs_kurs/__init__.py
nbs_kurs/__main__.py
nbs_kurs/cli.py
nbs_kurs/data_helper.py
nbs_kurs/date_helper.py
nbs_kurs/get_values_from_nbs.py
nbs_kurs/presentation_helper.py
nbs_srednji_kurs-1.2.0.dist-info/METADATA
nbs_srednji_kurs-1.2.0.dist-info/WHEEL
nbs_srednji_kurs-1.2.0.dist-info/entry_points.txt
nbs_srednji_kurs-1.2.0.dist-info/top_level.txt
nbs_srednji_kurs-1.2.0.dist-info/RECORD
