Metadata-Version: 2.4
Name: nbs-srednji-kurs
Version: 1.2.0
Summary: Get average currency values for Serbia
Author-email: Ivan Miletic <milemik68@gmail.com>
Requires-Python: >=3.12
Requires-Dist: beautifulsoup4>=4.13.4
Requires-Dist: requests>=2.32.4
Requires-Dist: rich>=14.1.0
